AUTHORS
CHANGELOG
INSTALL
LICENSE
MANIFEST.in
README
README.md
setup.py
docs/Makefile
docs/conf.py
docs/default-backend.rst
docs/faq.rst
docs/forms.rst
docs/index.rst
docs/make.bat
docs/quickstart.rst
docs/release-notes.rst
docs/signals.rst
docs/simple-backend.rst
docs/upgrade.rst
docs/views.rst
opps/__init__.py
opps/registration/__init__.py
opps/registration/admin.py
opps/registration/auth_urls.py
opps/registration/fields.py
opps/registration/forms.py
opps/registration/models.py
opps/registration/signals.py
opps/registration/urls.py
opps/registration/utils.py
opps/registration/views.py
opps/registration/widgets.py
opps/registration/backends/__init__.py
opps/registration/backends/default/__init__.py
opps/registration/backends/default/urls.py
opps/registration/backends/default/views.py
opps/registration/backends/simple/__init__.py
opps/registration/backends/simple/urls.py
opps/registration/backends/simple/views.py
opps/registration/locale/ar/LC_MESSAGES/django.mo
opps/registration/locale/ar/LC_MESSAGES/django.po
opps/registration/locale/bg/LC_MESSAGES/django.mo
opps/registration/locale/bg/LC_MESSAGES/django.po
opps/registration/locale/ca/LC_MESSAGES/django.mo
opps/registration/locale/ca/LC_MESSAGES/django.po
opps/registration/locale/cs/LC_MESSAGES/django.mo
opps/registration/locale/cs/LC_MESSAGES/django.po
opps/registration/locale/da/LC_MESSAGES/django.mo
opps/registration/locale/da/LC_MESSAGES/django.po
opps/registration/locale/de/LC_MESSAGES/django.mo
opps/registration/locale/de/LC_MESSAGES/django.po
opps/registration/locale/el/LC_MESSAGES/django.mo
opps/registration/locale/el/LC_MESSAGES/django.po
opps/registration/locale/en/LC_MESSAGES/django.mo
opps/registration/locale/en/LC_MESSAGES/django.po
opps/registration/locale/en_US/LC_MESSAGES/django.po
opps/registration/locale/es/LC_MESSAGES/django.mo
opps/registration/locale/es/LC_MESSAGES/django.po
opps/registration/locale/es_AR/LC_MESSAGES/django.mo
opps/registration/locale/es_AR/LC_MESSAGES/django.po
opps_registration.egg-info/PKG-INFO
opps_registration.egg-info/SOURCES.txt
opps_registration.egg-info/dependency_links.txt
opps_registration.egg-info/namespace_packages.txt
opps_registration.egg-info/requires.txt
opps_registration.egg-info/top_level.txt